handler.py
risk_detector/__init__.py
risk_detector/auto_refresh.py
risk_detector/auto_rules.py
risk_detector/cli.py
risk_detector/coverage.py
risk_detector/dialog_orchestrator.py
risk_detector/models.py
risk_detector/partial_eval.py
risk_detector/question_builder.py
risk_detector/classifiers/__init__.py
risk_detector/classifiers/aggregator.py
risk_detector/evaluators/__init__.py
risk_detector/evaluators/jsonlogic_eval.py
annex4risk_detector-1.4.9.dist-info/METADATA
annex4risk_detector-1.4.9.dist-info/WHEEL
annex4risk_detector-1.4.9.dist-info/entry_points.txt
annex4risk_detector-1.4.9.dist-info/top_level.txt
annex4risk_detector-1.4.9.dist-info/RECORD
