Metadata-Version: 2.4
Name: annex4risk-detector
Version: 1.4.9
Summary: risk classification chat assistant
Author-email: Aleksandr Racionalus <prihodko02bk@gmail.com>
Requires-Python: >=3.8
Requires-Dist: click>=8.0
Requires-Dist: PyYAML>=6.0
Requires-Dist: SQLAlchemy>=1.4
Requires-Dist: alembic>=1.12
Requires-Dist: psycopg2-binary>=2.9
Requires-Dist: openai>=1.0
Requires-Dist: jsonschema>=4.0
Provides-Extra: test
Requires-Dist: pytest>=7.0; extra == "test"
Requires-Dist: boto3>=1.28; extra == "test"
